Metadata-Version: 2.1
Name: cached-contingency
Version: 0.0.4
Summary: Compute and cache Fisher's exact test and Boschloo's test more efficiently!
Home-page: https://github.com/MrTomRod/cached-contingency
Author: Thomas Roder
Author-email: roder.thomas@gmail.com
License: MIT
Platform: UNKNOWN
Classifier: License :: OSI Approved :: MIT License
Classifier: Programming Language :: Python :: 3
Classifier: Programming Language :: Python :: 3.9
Classifier: Programming Language :: Python :: 3.10
License-File: LICENCE.md
